mfcs_memory/__init__.py
mfcs_memory/user_memory/__init__.py
mfcs_memory/user_memory/base.py
mfcs_memory/user_memory/conversation_analyzer.py
mfcs_memory/user_memory/memory_manager.py
mfcs_memory/user_memory/session_manager.py
mfcs_memory/user_memory/vector_store.py
mfcs_memory/utils/__init__.py
mfcs_memory/utils/config.py
mfcs_memory-0.2.3.dist-info/licenses/LICENSE
mfcs_memory-0.2.3.dist-info/METADATA
mfcs_memory-0.2.3.dist-info/WHEEL
mfcs_memory-0.2.3.dist-info/top_level.txt
mfcs_memory-0.2.3.dist-info/RECORD
