Metadata-Version: 2.4
Name: mfcs-memory
Version: 0.2.3
Summary: A smart conversation memory management system
Home-page: https://github.com/mfcsorg/mfcs-memory
Author: shideqin
Author-email: shisdq@gmail.com
Classifier: Development Status :: 3 - Alpha
Classifier: Intended Audience :: Developers
Classifier: License :: OSI Approved :: MIT License
Classifier: Operating System :: OS Independent
Classifier: Programming Language :: Python :: 3
Classifier: Programming Language :: Python :: 3.8
Classifier: Programming Language :: Python :: 3.9
Classifier: Programming Language :: Python :: 3.10
Requires-Python: >=3.8
License-File: LICENSE
Requires-Dist: pymongo
Requires-Dist: python-dotenv
Requires-Dist: qdrant-client
Requires-Dist: openai==1.86.0
Requires-Dist: sentence-transformers
Dynamic: author
Dynamic: author-email
Dynamic: classifier
Dynamic: description
Dynamic: description-content-type
Dynamic: home-page
Dynamic: license-file
Dynamic: requires-dist
Dynamic: requires-python
Dynamic: summary
